terracommon/__init__.py
terracommon/data_importers/__init__.py
terracommon/data_importers/apps.py
terracommon/data_importers/management/__init__.py
terracommon/data_importers/management/commands/__init__.py
terracommon/data_importers/management/commands/import_csv_users.py
terracommon/datastore/__init__.py
terracommon/datastore/apps.py
terracommon/datastore/fields.py
terracommon/datastore/managers.py
terracommon/datastore/models.py
terracommon/datastore/permissions.py
terracommon/datastore/serializers.py
terracommon/datastore/tests.py
terracommon/datastore/urls.py
terracommon/datastore/views.py
terracommon/datastore/migrations/0001_initial.py
terracommon/datastore/migrations/0002_auto_20181024_1609.py
terracommon/datastore/migrations/0003_auto_20181120_1059.py
terracommon/datastore/migrations/0004_relateddocument_properties.py
terracommon/datastore/migrations/__init__.py
terracommon/document_generator/__init__.py
terracommon/document_generator/apps.py
terracommon/document_generator/filters.py
terracommon/document_generator/helpers.py
terracommon/document_generator/models.py
terracommon/document_generator/serializers.py
terracommon/document_generator/settings.py
terracommon/document_generator/urls.py
terracommon/document_generator/views.py
terracommon/document_generator/management/__init__.py
terracommon/document_generator/management/commands/__init__.py
terracommon/document_generator/management/commands/generate_document.py
terracommon/document_generator/migrations/0001_initial.py
terracommon/document_generator/migrations/0002_documenttemplate_uid.py
terracommon/document_generator/migrations/0003_auto_20180911_0827.py
terracommon/document_generator/migrations/0004_auto_20181012_0755.py
terracommon/document_generator/migrations/0005_auto_20181120_1059.py
terracommon/document_generator/migrations/__init__.py
terracommon/events/__init__.py
terracommon/events/apps.py
terracommon/events/models.py
terracommon/events/management/__init__.py
terra_common-0.3.4.dist-info/LICENSE
terra_common-0.3.4.dist-info/METADATA
terra_common-0.3.4.dist-info/WHEEL
terra_common-0.3.4.dist-info/top_level.txt
terra_common-0.3.4.dist-info/RECORD
